stpipe/__init__.py
stpipe/__main__.py
stpipe/_version.py
stpipe/cmdline.py
stpipe/config.py
stpipe/config_parser.py
stpipe/crds_client.py
stpipe/datamodel.py
stpipe/entry_points.py
stpipe/exceptions.py
stpipe/format_template.py
stpipe/function_wrapper.py
stpipe/hooks.py
stpipe/integration.py
stpipe/library.py
stpipe/log.py
stpipe/pipeline.py
stpipe/step.py
stpipe/subproc.py
stpipe/utilities.py
stpipe/cli/__init__.py
stpipe/cli/command.py
stpipe/cli/list.py
stpipe/cli/main.py
stpipe/cli/strun.py
stpipe/extern/__init__.py
stpipe/extern/configobj.py
stpipe/resources/__init__.py
stpipe/resources/schemas/step_config-0.1.0.yaml
stpipe/resources/schemas/step_config-1.0.0.yaml
stpipe/resources/schemas/step_config_with_metadata-1.0.0.yaml
stpipe-0.11.1.dist-info/licenses/LICENSE
stpipe-0.11.1.dist-info/METADATA
stpipe-0.11.1.dist-info/WHEEL
stpipe-0.11.1.dist-info/entry_points.txt
stpipe-0.11.1.dist-info/top_level.txt
stpipe-0.11.1.dist-info/zip-safe
stpipe-0.11.1.dist-info/RECORD
