Metadata-Version: 2.4
Name: stpipe
Version: 0.11.1
Summary: Framework for calibration pipeline software
Author-email: STScI <help@stsci.edu>
Project-URL: repository, https://github.com/spacetelescope/stpipe
Project-URL: tracker, https://github.com/spacetelescope/stpipe/issues
Classifier: Intended Audience :: Science/Research
Classifier: Topic :: Scientific/Engineering :: Astronomy
Classifier: Programming Language :: Python :: 3
Requires-Python: >=3.10
License-File: LICENSE
Requires-Dist: asdf>=2.13
Requires-Dist: crds>=7.4.1.3
Requires-Dist: astropy>=5.0.4
Requires-Dist: importlib_metadata>=4.11.4
Requires-Dist: pyyaml>=5
Provides-Extra: docs
Requires-Dist: numpydoc; extra == "docs"
Requires-Dist: sphinx; extra == "docs"
Requires-Dist: sphinx-automodapi; extra == "docs"
Requires-Dist: sphinx-rtd-theme; extra == "docs"
Requires-Dist: tomli; python_version < "3.11" and extra == "docs"
Provides-Extra: test
Requires-Dist: pytest>=7.0.0; extra == "test"
Requires-Dist: pytest-doctestplus>=0.10.0; extra == "test"
Dynamic: license-file
